{
  "(0, 0, 2)": "Bring Me the Horizon",
  "(1, 0, 1)": "Origin",
  "(1, 1, 1)": "Sheffield, South Yorkshire, England",
  "(2, 0, 1)": "Genres",
  "(2, 1, 1)": "Metalcore, alternative metal, alternative rock, post-hardcore, electronic rock, deathcore (early)",
  "(3, 0, 1)": "Years active",
  "(3, 1, 1)": "2004 present",
  "(4, 0, 1)": "Labels",
  "(4, 1, 1)": "BMG, Sony, RCA, Columbia, Visible Noise, Epitaph, Thirty Days of Night, Earache, Shock",
  "(5, 0, 1)": "Website",
  "(5, 1, 1)": "bmthofficial.com"
}