{
  "(0, 0, 1)": "Motto",
  "(0, 1, 1)": "Numen Lumen (Latin)",
  "(1, 0, 1)": "Motto in English",
  "(1, 1, 1)": "\"God, our light\" or , \"The divine within the universe, however manifested, is my light.\"",
  "(2, 0, 1)": "Type",
  "(2, 1, 1)": "Public university flagship, Land-grant university, Sea-grant university",
  "(3, 0, 1)": "Established",
  "(3, 1, 1)": "1848",
  "(4, 0, 1)": "Affiliation",
  "(4, 1, 1)": "UW System",
  "(5, 0, 1)": "Academic affiliation",
  "(5, 1, 1)": "AAU, URA, APLU, BTAA, WUN, ",
  "(6, 0, 1)": "Endowment",
  "(6, 1, 1)": "$2.746 billion (2017)",
  "(7, 0, 1)": "Chancellor",
  "(7, 1, 1)": "Rebecca Blank",
  "(8, 0, 1)": "Academic staff",
  "(8, 1, 1)": "2,220",
  "(9, 0, 1)": "Students",
  "(9, 1, 1)": "44,413 (fall 2018)",
  "(10, 0, 1)": "Undergraduates",
  "(10, 1, 1)": "30,361 (fall 2018)",
  "(11, 0, 1)": "Postgraduates",
  "(11, 1, 1)": "14,052 (fall 2018)",
  "(12, 0, 1)": "Location",
  "(12, 1, 1)": "Madison, Wisconsin, U.S., 43°04′30″N 89°25′02″W﻿ / ﻿43.075000°N 89.417222°W﻿ / 43.075000; -89.417222Coordinates: 43°04′30″N 89°25′02″W﻿ / ﻿43.075000°N 89.417222°W﻿ / 43.075000; -89.417222",
  "(13, 0, 1)": "Campus",
  "(13, 1, 1)": "Urban,  936 acres (379 ha)",
  "(14, 0, 1)": "Colors",
  "(14, 1, 1)": "Cardinal and white,          ",
  "(15, 0, 1)": "Athletics",
  "(15, 1, 1)": "NCAA Division I – Big Ten, WCHA (Women's ice hockey)",
  "(16, 0, 1)": "Nickname",
  "(16, 1, 1)": "Badgers",
  "(17, 0, 1)": "Mascot",
  "(17, 1, 1)": "Bucky Badger",
  "(18, 0, 1)": "Website",
  "(18, 1, 1)": "www.wisc.edu"
}