{
  "(0, 0, 2)": "Jennifer Aniston",
  "(1, 0, 1)": "Born",
  "(1, 1, 1)": "Jennifer Joanna Aniston,  (1969-02-11) February 11, 1969 (age 49), Sherman Oaks, California, U.S.",
  "(2, 0, 1)": "Residence",
  "(2, 1, 1)": "Bel Air, California, U.S.",
  "(3, 0, 1)": "Education",
  "(3, 1, 1)": "Fiorello H. LaGuardia High School of Music & Art and Performing Arts",
  "(4, 0, 1)": "Occupation",
  "(4, 1, 1)": "Actress, film producer, businesswoman",
  "(5, 0, 1)": "Years active",
  "(5, 1, 1)": "1987 present",
  "(6, 0, 1)": "Net worth",
  "(6, 1, 1)": "US$200 million, (May 2017 estimate)",
  "(7, 0, 1)": "Spouse(s)",
  "(7, 1, 1)": "Brad Pitt, (m. 2000; div. 2005), Justin Theroux, (m. 2015; sep. 2017)",
  "(8, 0, 1)": "Parent(s)",
  "(8, 1, 1)": "Nancy Dow, John Aniston"
}