{
  "(0, 0, 2)": "John Ernst Worrell Keely",
  "(1, 0, 1)": "Born",
  "(1, 1, 1)": "(1837-09-03)September 3, 1837, Chester, Pennsylvania",
  "(2, 0, 1)": "Died",
  "(2, 1, 1)": "November 18, 1898(1898-11-18) (aged 61), Philadelphia, Pennsylvania",
  "(3, 0, 1)": "Cause of death",
  "(3, 1, 1)": "Pneumonia",
  "(4, 0, 1)": "Burial place",
  "(4, 1, 1)": "West Laurel Hill Cemetery in Bala Cynwyd, Pennsylvania",
  "(5, 0, 1)": "Nationality",
  "(5, 1, 1)": "American",
  "(6, 0, 1)": "Occupation",
  "(6, 1, 1)": "Inventor",
  "(7, 0, 1)": "Years active",
  "(7, 1, 1)": "1872 (1872) 1897 (1897)",
  "(8, 0, 1)": "Organization",
  "(8, 1, 1)": "Keely Motor Company",
  "(9, 0, 1)": "Notable work",
  "(9, 1, 1)": "Keely engine",
  "(10, 0, 1)": "Home town",
  "(10, 1, 1)": "Philadelphia"
}