{
  "(0, 0, 2)": "Isle of Dogs",
  "(1, 0, 1)": "Directed by",
  "(1, 1, 1)": "Wes Anderson",
  "(2, 0, 1)": "Produced by",
  "(2, 1, 1)": "Wes Anderson, Scott Rudin, Steven Rales, Jeremy Dawson, ",
  "(3, 0, 1)": "Screenplay by",
  "(3, 1, 1)": "Wes Anderson",
  "(4, 0, 1)": "Story by",
  "(4, 1, 1)": "Wes Anderson, Roman Coppola, Jason Schwartzman, Kunichi Nomura, ",
  "(5, 0, 1)": "Starring",
  "(5, 1, 1)": "Koyu Rankin, Bryan Cranston, Edward Norton, Bill Murray, Jeff Goldblum, Bob Balaban, Kunichi Nomura, Ken Watanabe, Greta Gerwig, Frances McDormand, Fisher Stevens, Harvey Keitel, Liev Schreiber, Scarlett Johansson, Tilda Swinton, F. Murray Abraham, ",
  "(6, 0, 1)": "Narrated by",
  "(6, 1, 1)": "Courtney B. Vance",
  "(7, 0, 1)": "Music by",
  "(7, 1, 1)": "Alexandre Desplat",
  "(8, 0, 1)": "Cinematography",
  "(8, 1, 1)": "Tristan Oliver",
  "(9, 0, 1)": "Edited by",
  "(9, 1, 1)": "Ralph Foster, Edward Bursch, ",
  "(10, 0, 1)": "Production, company ",
  "(10, 1, 1)": "Studio Babelsberg, Indian Paintbrush, American Empirical Pictures,  ",
  "(11, 0, 1)": "Distributed by",
  "(11, 1, 1)": "Fox Searchlight Pictures",
  "(12, 0, 1)": "Release date",
  "(12, 1, 1)": "February 15, 2018 (2018-02-15) (Berlinale), March 23, 2018 (2018-03-23) (United States), May 10, 2018 (2018-05-10) (Germany), , , ",
  "(13, 0, 1)": "Running time",
  "(13, 1, 1)": "101 minutes",
  "(14, 0, 1)": "Country",
  "(14, 1, 1)": "United States, Germany, ",
  "(15, 0, 1)": "Language",
  "(15, 1, 1)": "English , Japanese",
  "(16, 0, 1)": "Box office",
  "(16, 1, 1)": "$64.2 million"
}