{
  "(0, 0, 2)": "Burning Man",
  "(1, 0, 1)": "Begins",
  "(1, 1, 1)": "August 25, 2019",
  "(2, 0, 1)": "Ends",
  "(2, 1, 1)": "September 2, 2019",
  "(3, 0, 1)": "Frequency",
  "(3, 1, 1)": "Annual",
  "(4, 0, 1)": "Venue",
  "(4, 1, 1)": "Black Rock City",
  "(5, 0, 1)": "Location(s)",
  "(5, 1, 1)": "Black Rock Desert,, Pershing County, Nevada, US",
  "(6, 0, 1)": "Coordinates",
  "(6, 1, 1)": "40 47 13 N 119 12 22 W  /  40.787 N 119.206 W  / 40.787; -119.206Coordinates: 40 47 13 N 119 12 22 W  /  40.787 N 119.206 W  / 40.787; -119.206",
  "(7, 0, 1)": "Years active",
  "(7, 1, 1)": "33",
  "(8, 0, 1)": "Inaugurated",
  "(8, 1, 1)": "June 21, 1986 (1986-06-21)",
  "(9, 0, 1)": "Founders",
  "(9, 1, 1)": "Larry Harvey, John Law, Jerry James",
  "(10, 0, 1)": "Attendance",
  "(10, 1, 1)": "67,290 (2016)",
  "(11, 0, 1)": "Website",
  "(11, 1, 1)": "burningman.org"
}