{
  "(0, 0, 2)": "Halloween",
  "(1, 0, 1)": "Also called",
  "(1, 1, 1)": "Hallowe'en, Allhallowe'en, All Hallows' Eve, All Saints' Eve, ",
  "(2, 0, 1)": "Observed by",
  "(2, 1, 1)": "Western Christians and many non-Christians around the world",
  "(3, 0, 1)": "Significance",
  "(3, 1, 1)": "First day of Allhallowtide",
  "(4, 0, 1)": "Celebrations",
  "(4, 1, 1)": "Trick-or-treating, costume parties, making jack-o'-lanterns, lighting bonfires, divination, apple bobbing, visiting haunted attractions",
  "(5, 0, 1)": "Observances",
  "(5, 1, 1)": "Church services, prayer, fasting, and vigil",
  "(6, 0, 1)": "Date",
  "(6, 1, 1)": "31 October",
  "(7, 0, 1)": "Related to",
  "(7, 1, 1)": "Totensonntag, Blue Christmas, Thursday of the Dead, Samhain, Hop-tu-Naa, Calan Gaeaf, Allantide, Day of the Dead, Reformation Day, All Saints' Day, Mischief Night (cf. vigil)"
}