{
  "(0, 0, 1)": "Traded as",
  "(0, 1, 1)": "NASDAQ: ACTA",
  "(1, 0, 1)": "Industry",
  "(1, 1, 1)": "Business-to-business",
  "(2, 0, 1)": "Fate",
  "(2, 1, 1)": "Underwent liquidation",
  "(3, 0, 1)": "Founded",
  "(3, 1, 1)": "March 4, 1996; 23 years ago (1996-03-04)",
  "(4, 0, 1)": "Founder",
  "(4, 1, 1)": "Ken Fox, Walter Buckley",
  "(5, 0, 1)": "Defunct",
  "(5, 1, 1)": "April 18, 2018; 19 months ago (2018-04-18)",
  "(6, 0, 1)": "Headquarters",
  "(6, 1, 1)": "Radnor, Pennsylvania",
  "(7, 0, 1)": "Website",
  "(7, 1, 1)": "www.actua.com"
}