{
  "(0, 0, 2)": "Dennis Ritchie",
  "(1, 0, 1)": "Born",
  "(1, 1, 1)": "(1941-09-09)September 9, 1941, Bronxville, New York, U.S.",
  "(2, 0, 1)": "Died",
  "(2, 1, 1)": "c. October 12, 2011(2011-10-12) (aged 70), Berkeley Heights, New Jersey, U.S.",
  "(3, 0, 1)": "Nationality",
  "(3, 1, 1)": "American",
  "(4, 0, 1)": "Alma mater",
  "(4, 1, 1)": "Harvard University (Ph.D., 1968)",
  "(5, 0, 1)": "Known for",
  "(5, 1, 1)": "ALTRAN, B, BCPL, C, Multics, Unix",
  "(6, 0, 1)": "Awards",
  "(6, 1, 1)": "Turing Award (1983), National Medal of Technology (1998), IEEE Richard W. Hamming Medal (1990), Computer Pioneer Award (1994), Computer History Museum Fellow (1997), Harold Pender Award (2003), Japan Prize (2011)",
  "(7, 0, 2)": "Scientific career",
  "(8, 0, 1)": "Fields",
  "(8, 1, 1)": "Computer science",
  "(9, 0, 1)": "Institutions",
  "(9, 1, 1)": "Lucent Technologies, Bell Labs"
}