{
  "(0, 0, 2)": "Dave Navarro",
  "(1, 0, 1)": "Birth name",
  "(1, 1, 1)": "David Michael Navarro",
  "(2, 0, 1)": "Born",
  "(2, 1, 1)": "(1967-06-07) June 7, 1967 (age 51), Santa Monica, California, U.S.",
  "(3, 0, 1)": "Genres",
  "(3, 1, 1)": "Alternative rock, hard rock",
  "(4, 0, 1)": "Instruments",
  "(4, 1, 1)": "Guitar, vocals",
  "(5, 0, 1)": "Years active",
  "(5, 1, 1)": "1986-present",
  "(6, 0, 1)": "Labels",
  "(6, 1, 1)": "Warner, Capitol",
  "(7, 0, 1)": "Associated acts",
  "(7, 1, 1)": "Jane's Addiction, Red Hot Chili Peppers, Mike Hawk, Deconstruction, The Panic Channel, Camp Freddy, Spirits in the Sky, Marilyn Manson, Guns N' Roses, Nine Inch Nails, Alanis Morissette, Finger Eleven"
}