{
  "(0, 0, 2)": "Dan Borislow",
  "(1, 0, 1)": "Born",
  "(1, 1, 1)": "(1961-09-21)September 21, 1961, Philadelphia, Pennsylvania",
  "(2, 0, 1)": "Died",
  "(2, 1, 1)": "July 21, 2014(2014-07-21) (aged 52), West Palm Beach, Florida",
  "(3, 0, 1)": "Residence",
  "(3, 1, 1)": "Palm Beach County, Florida",
  "(4, 0, 1)": "Occupation",
  "(4, 1, 1)": "Telecommunications, Horse breeding",
  "(5, 0, 1)": "Spouse(s)",
  "(5, 1, 1)": "Michele (Shelly)",
  "(6, 0, 1)": "Children",
  "(6, 1, 1)": "Danny, Kylie"
}