{
  "(0, 0, 2)": "Celine Dion",
  "(0, 1, 1)": "CC OQ ChLD",
  "(1, 0, 1)": "Born",
  "(1, 1, 1)": "Céline Marie Claudette Dion",
  "(1, 2, 1)": "(1968-03-30) 30 March 1968 (age 50)",
  "(1, 3, 1)": "Charlemagne, Quebec, Canada",
  "(2, 0, 1)": "Residence",
  "(2, 1, 1)": "Henderson, Nevada, U.S.",
  "(3, 0, 1)": "Occupation",
  "(3, 1, 1)": "Singer",
  "(4, 0, 1)": "Years active",
  "(4, 1, 1)": "1980-present",
  "(5, 0, 1)": "Net worth",
  "(5, 1, 1)": "$700 million",
  "(6, 0, 1)": "Spouse(s)",
  "(6, 1, 1)": "René Angélil",
  "(6, 2, 1)": "(m. 1994; died 2016)",
  "(7, 0, 1)": "Children",
  "(7, 1, 1)": "3",
  "(8, 0, 1)": "Parent(s)",
  "(8, 1, 1)": "Adhémar-Charles Dion",
  "(8, 2, 1)": "Thérèse Tanguay Dion",
  "(9, 0, 2)": "Musical career",
  "(10, 0, 1)": "Genres",
  "(10, 1, 1)": "Pop",
  "(10, 2, 1)": "chanson",
  "(10, 3, 1)": "soft rock",
  "(10, 4, 1)": "R&B",
  "(11, 0, 1)": "Instruments",
  "(11, 1, 1)": "Vocals",
  "(12, 0, 1)": "Labels",
  "(12, 1, 1)": "CBS",
  "(12, 2, 1)": "Epic",
  "(12, 3, 1)": "Columbia",
  "(12, 4, 1)": "550",
  "(12, 5, 1)": "Legacy",
  "(13, 0, 1)": "Associated acts",
  "(13, 1, 1)": "David Foster",
  "(14, 0, 1)": "Website",
  "(14, 1, 1)": "celinedion.com"
}