{
  "(0, 0, 2)": "Harvard University",
  "(1, 0, 2)": "Latin: Universitas Harvardiana",
  "(2, 0, 1)": "Former names",
  "(2, 1, 1)": "Harvard College",
  "(3, 0, 1)": "Motto",
  "(3, 1, 1)": "Veritas",
  "(4, 0, 1)": "Motto in English",
  "(4, 1, 1)": "Truth",
  "(5, 0, 1)": "Type",
  "(5, 1, 1)": "Private nonprofit university",
  "(6, 0, 1)": "Established",
  "(6, 1, 1)": "1636 (1636)",
  "(7, 0, 1)": "Endowment",
  "(7, 1, 1)": "US$38.3 billion (FY 2018)",
  "(8, 0, 1)": "President",
  "(8, 1, 1)": "Lawrence S. Bacow",
  "(9, 0, 1)": "Academic staff",
  "(9, 1, 1)": "4,671",
  "(10, 0, 1)": "Students",
  "(10, 1, 1)": "22,000",
  "(11, 0, 1)": "Undergraduates",
  "(11, 1, 1)": "6,700",
  "(12, 0, 1)": "Postgraduates",
  "(12, 1, 1)": "15,250",
  "(13, 0, 1)": "Location",
  "(13, 1, 1)": "Cambridge, Massachusetts",
  "(13, 2, 1)": "42 22 28 N 71 07 01 W  /  42.37444 N 71.11694 W  / 42.37444; -71.11694Coordinates: 42 22 28 N 71 07 01 W  /  42.37444 N 71.11694 W  / 42.37444; -71.11694",
  "(14, 0, 1)": "Campus",
  "(14, 1, 1)": "Urban",
  "(14, 2, 1)": "210 acres (85 ha)",
  "(15, 0, 1)": "Newspaper",
  "(15, 1, 1)": "The Harvard Crimson",
  "(16, 0, 1)": "Colors",
  "(16, 1, 1)": "Crimson",
  "(17, 0, 1)": "Athletics",
  "(17, 1, 1)": "NCAA Division I - Ivy League",
  "(18, 0, 1)": "Nickname",
  "(18, 1, 1)": "Harvard Crimson",
  "(19, 0, 1)": "Affiliations",
  "(19, 1, 1)": "NAICU",
  "(19, 2, 1)": "AICUM",
  "(19, 3, 1)": "AAU",
  "(19, 4, 1)": "URA",
  "(20, 0, 1)": "Website",
  "(20, 1, 1)": "harvard.edu"
}