{
  "(0, 0, 2)": "Icona Pop",
  "(1, 0, 1)": "Origin",
  "(1, 1, 1)": "Stockholm, Sweden",
  "(2, 0, 1)": "Genres",
  "(2, 1, 1)": "Electropop",
  "(2, 2, 1)": "dance-pop",
  "(2, 3, 1)": "synth-pop",
  "(2, 4, 1)": "electro house",
  "(3, 0, 1)": "Years active",
  "(3, 1, 1)": "2009-present",
  "(4, 0, 1)": "Labels",
  "(4, 1, 1)": "TEN",
  "(4, 2, 1)": "Big Beat",
  "(4, 3, 1)": "Atlantic",
  "(5, 0, 1)": "Associated acts",
  "(5, 1, 1)": "Chiddy Bang",
  "(5, 2, 1)": "Ti sto",
  "(5, 3, 1)": "Charli XCX",
  "(5, 4, 1)": "The Cataracs",
  "(5, 5, 1)": "Cobra Starship",
  "(5, 6, 1)": "Travie McCoy",
  "(5, 7, 1)": "Tove Lo",
  "(5, 8, 1)": "One Direction",
  "(5, 9, 1)": "Sirah",
  "(5, 10, 1)": "Lowell",
  "(5, 11, 1)": "Peking Duk",
  "(6, 0, 1)": "Website",
  "(6, 1, 1)": "iconapop.com"
}