{
  "(0, 0, 2)": "Prader-Willi syndrome",
  "(1, 0, 1)": "Other names",
  "(1, 1, 1)": "Labhart-Willi syndrome, Prader's syndrome, Prader-Labhart-Willi-Fanconi syndrome",
  "(2, 0, 1)": "Pronunciation",
  "(2, 1, 1)": "/ pr d r  v li/, / pre d r w li/, / pr d r  w li/",
  "(3, 0, 1)": "Specialty",
  "(3, 1, 1)": "Medical genetics, psychiatry, pediatrics",
  "(4, 0, 1)": "Symptoms",
  "(4, 1, 1)": "Babies: weak muscles, poor feeding, slow development",
  "(4, 2, 1)": "Children: constantly hungry, intellectual impairment, behavioural problems",
  "(5, 0, 1)": "Complications",
  "(5, 1, 1)": "Obesity, type 2 diabetes",
  "(6, 0, 1)": "Duration",
  "(6, 1, 1)": "Lifelong",
  "(7, 0, 1)": "Causes",
  "(7, 1, 1)": "Genetic disorder (typically new mutation)",
  "(8, 0, 1)": "Differential diagnosis",
  "(8, 1, 1)": "Spinal muscular atrophy, congenital myotonic dystrophy, familial obesity",
  "(9, 0, 1)": "Treatment",
  "(9, 1, 1)": "Feeding tubes, strict food supervision, exercise program, counseling",
  "(10, 0, 1)": "Medication",
  "(10, 1, 1)": "Growth hormone therapy",
  "(11, 0, 1)": "Frequency",
  "(11, 1, 1)": "1 in 10,000-30,000 people"
}