{
  "(0, 0, 2)": "The Most Reverend",
  "(0, 1, 1)": "Desmond Tutu",
  "(0, 2, 1)": "OMSG CH GCStJ",
  "(1, 0, 2)": "Archbishop Emeritus of Cape Town",
  "(2, 0, 1)": "Church",
  "(2, 1, 1)": "Anglican Church of Southern Africa",
  "(3, 0, 1)": "See",
  "(3, 1, 1)": "Cape Town (retired)",
  "(4, 0, 1)": "Installed",
  "(4, 1, 1)": "7 September 1986",
  "(5, 0, 1)": "Term ended",
  "(5, 1, 1)": "1996",
  "(6, 0, 1)": "Predecessor",
  "(6, 1, 1)": "Philip Russell",
  "(7, 0, 1)": "Successor",
  "(7, 1, 1)": "Njongonkulu Ndungane",
  "(8, 0, 1)": "Other posts",
  "(8, 1, 1)": "Bishop of Lesotho",
  "(8, 2, 1)": "Bishop of Johannesburg",
  "(8, 3, 1)": "Archbishop of Cape Town",
  "(9, 0, 2)": "Orders",
  "(10, 0, 1)": "Ordination",
  "(10, 1, 1)": "Deacon 1960",
  "(10, 2, 1)": "Priest 1961",
  "(11, 0, 1)": "Consecration",
  "(11, 1, 1)": "1976",
  "(12, 0, 2)": "Personal details",
  "(13, 0, 1)": "Birth name",
  "(13, 1, 1)": "Desmond Mpilo Tutu",
  "(14, 0, 1)": "Born",
  "(14, 1, 1)": "(1931-10-07) 7 October 1931 (age 88)",
  "(14, 2, 1)": "Klerksdorp, Western Transvaal, South Africa",
  "(15, 0, 1)": "Spouse",
  "(15, 1, 1)": "Nomalizo Leah Shenxane (m. 1955)",
  "(16, 0, 1)": "Children",
  "(16, 1, 1)": "Mpho Tutu, Theresa Tutu, Naomi Tutu, Trevor Tutu",
  "(17, 0, 1)": "Education",
  "(17, 1, 1)": "King's College London",
  "(18, 0, 1)": "Alma mater",
  "(18, 1, 1)": "King's College London"
}