{
  "(0, 0, 2)": "MyRepublic",
  "(1, 0, 1)": "Type",
  "(1, 1, 1)": "Private",
  "(2, 0, 1)": "Industry",
  "(2, 1, 1)": "Telecommunication",
  "(3, 0, 1)": "Founded",
  "(3, 1, 1)": "2011; 8 years ago (2011)",
  "(4, 0, 1)": "Headquarters",
  "(4, 1, 1)": "Singapore",
  "(5, 0, 1)": "Areas served",
  "(5, 1, 1)": "Singapore",
  "(5, 2, 1)": "New Zealand",
  "(5, 3, 1)": "Indonesia",
  "(5, 4, 1)": "Australia",
  "(6, 0, 1)": "Key people",
  "(6, 1, 1)": "Malcolm Rodrigues (CEO)",
  "(6, 2, 1)": "Greg Mittman (COO)",
  "(6, 3, 1)": "KC Lai (CCO)",
  "(7, 0, 1)": "Services",
  "(7, 1, 1)": "High-speed fibre broadband",
  "(7, 2, 1)": "Home and Business Voice",
  "(7, 3, 1)": "Managed services for Business",
  "(7, 4, 1)": "TV Services",
  "(8, 0, 1)": "Number of employees",
  "(8, 1, 1)": "Approximately 230",
  "(9, 0, 1)": "Website",
  "(9, 1, 1)": "myrepublic.net"
}