{
  "(0, 0, 2)": "\"Dark Globe\"",
  "(1, 0, 2)": "Song by Syd Barrett",
  "(2, 0, 2)": "from the album The Madcap Laughs",
  "(3, 0, 1)": "Published",
  "(3, 1, 1)": "Lupus Music Ltd",
  "(4, 0, 1)": "Released",
  "(4, 1, 1)": "3 January 1970",
  "(5, 0, 1)": "Recorded",
  "(5, 1, 1)": "12 June 1969",
  "(5, 2, 1)": "26 July 1969 (Opel version)",
  "(6, 0, 1)": "Genre",
  "(6, 1, 1)": "Folk",
  "(7, 0, 1)": "Length",
  "(7, 1, 1)": "2:02",
  "(7, 2, 1)": "3:00 (Opel version)",
  "(8, 0, 1)": "Label",
  "(8, 1, 1)": "Harvest (UK)",
  "(8, 2, 1)": "Capitol (U.S.)",
  "(9, 0, 1)": "Songwriter(s)",
  "(9, 1, 1)": "Syd Barrett",
  "(10, 0, 1)": "Producer(s)",
  "(10, 1, 1)": "David Gilmour",
  "(10, 2, 1)": "Roger Waters",
  "(11, 0, 2)": "The Madcap Laughs track listing",
  "(12, 0, 1)": "\"Terrapin\"",
  "(12, 1, 1)": "\"No Good Trying\"",
  "(12, 2, 1)": "\"Love You\"",
  "(12, 3, 1)": "\"No Man's Land\"",
  "(12, 4, 1)": "\"Dark Globe\"",
  "(12, 5, 1)": "\"Here I Go\"",
  "(12, 6, 1)": "\"Octopus\"",
  "(12, 7, 1)": "\"Golden Hair\"",
  "(12, 8, 1)": "\"Long Gone\"",
  "(12, 9, 1)": "\"She Took a Long Cold Look\"",
  "(12, 10, 1)": "\"Feel\"",
  "(12, 11, 1)": "\"If It's In You\"",
  "(12, 12, 1)": "\"Late Night\"",
  "(13, 0, 2)": "An Introduction to Syd Barrett track listing",
  "(14, 0, 1)": "\"Arnold Layne\"",
  "(14, 1, 1)": "\"See Emily Play\"",
  "(14, 2, 1)": "\"Apples and Oranges\"",
  "(14, 3, 1)": "\"Matilda Mother\"",
  "(14, 4, 1)": "\"Chapter 24\"",
  "(14, 5, 1)": "\"Bike\"",
  "(14, 6, 1)": "\"Terrapin\"",
  "(14, 7, 1)": "\"Love You\"",
  "(14, 8, 1)": "\"Dark Globe\"",
  "(14, 9, 1)": "\"Here I Go\"",
  "(14, 10, 1)": "\"Octopus\"",
  "(14, 11, 1)": "\"She Took a Long Cool Look\"",
  "(14, 12, 1)": "\"If It's In You\"",
  "(14, 13, 1)": "\"Baby Lemonade\"",
  "(14, 14, 1)": "\"Dominoes\"",
  "(14, 15, 1)": "\"Gigolo Aunt\"",
  "(14, 16, 1)": "\"Effervescing Elephant\"",
  "(14, 17, 1)": "\"Bob Dylan Blues\""
}