{
  "(0, 0, 2)": "James Taylor",
  "(1, 0, 1)": "Born",
  "(1, 1, 1)": "James Vernon Taylor",
  "(1, 2, 1)": "(1948-03-12) March 12, 1948 (age 70)",
  "(1, 3, 1)": "Boston, Massachusetts, U.S.",
  "(2, 0, 1)": "Nationality",
  "(2, 1, 1)": "American",
  "(3, 0, 1)": "Other names",
  "(3, 1, 1)": "James V. Taylor",
  "(4, 0, 1)": "Alma mater",
  "(4, 1, 1)": "Milton Academy",
  "(5, 0, 1)": "Occupation",
  "(5, 1, 1)": "Singer-songwriter",
  "(5, 2, 1)": "guitarist",
  "(6, 0, 1)": "Years active",
  "(6, 1, 1)": "1966 present",
  "(7, 0, 1)": "Home town",
  "(7, 1, 1)": "Chapel Hill, North Carolina, U.S.",
  "(8, 0, 1)": "Spouse(s)",
  "(8, 1, 1)": "Carly Simon",
  "(8, 2, 1)": "(m. 1972; div. 1983)",
  "(8, 3, 1)": "Kathryn Walker",
  "(8, 4, 1)": "(m. 1985; div. 1995)",
  "(8, 5, 1)": "Caroline \"Kim\" Smedvig (m. 2001)",
  "(9, 0, 1)": "Children",
  "(9, 1, 1)": "4; including Sally and Ben Taylor",
  "(10, 0, 1)": "Parent(s)",
  "(10, 1, 1)": "Isaac M. Taylor",
  "(10, 2, 1)": "Gertrude Woodard Taylor",
  "(11, 0, 1)": "Relatives",
  "(11, 1, 1)": "Alex Taylor (brother)",
  "(11, 2, 1)": "Kate Taylor (sister)",
  "(11, 3, 1)": "Livingston Taylor (brother)",
  "(12, 0, 2)": "Musical career",
  "(13, 0, 1)": "Genres",
  "(13, 1, 1)": "Folk rock",
  "(13, 2, 1)": "rock",
  "(13, 3, 1)": "pop",
  "(13, 4, 1)": "soft rock",
  "(13, 5, 1)": "blues",
  "(13, 6, 1)": "Christmas music",
  "(13, 7, 1)": "country folk",
  "(14, 0, 1)": "Instruments",
  "(14, 1, 1)": "Vocals",
  "(14, 2, 1)": "guitar",
  "(14, 3, 1)": "harmonica",
  "(14, 4, 1)": "keyboards",
  "(15, 0, 1)": "Labels",
  "(15, 1, 1)": "Apple",
  "(15, 2, 1)": "Capitol",
  "(15, 3, 1)": "EMI",
  "(15, 4, 1)": "Warner Bros.",
  "(15, 5, 1)": "Columbia",
  "(15, 6, 1)": "SME",
  "(15, 7, 1)": "Hear Music",
  "(16, 0, 1)": "Associated acts",
  "(16, 1, 1)": "Carole King",
  "(16, 2, 1)": "Carly Simon",
  "(16, 3, 1)": "Peter Asher",
  "(16, 4, 1)": "Joni Mitchell",
  "(16, 5, 1)": "Paul McCartney",
  "(17, 0, 1)": "Website",
  "(17, 1, 1)": "jamestaylor.com"
}