{
  "(0, 0, 2)": "David Gestetner (eng)",
  "(0, 1, 1)": "Gestetner D vid (hu)",
  "(1, 0, 1)": "Born",
  "(1, 1, 1)": "31 March 1854",
  "(1, 2, 1)": "Csorna, Kingdom of Hungary, Habsburg Empire",
  "(2, 0, 1)": "Died",
  "(2, 1, 1)": "8 March 1939 (1939-03-09) (aged 84)",
  "(2, 2, 1)": "London, United Kingdom",
  "(3, 0, 1)": "Known for",
  "(3, 1, 1)": "Gestetner, stencil duplicator, photocopier, nail clipper",
  "(4, 0, 1)": "Children",
  "(4, 1, 1)": "Sigmund Gestetner",
  "(5, 0, 1)": "Awards",
  "(5, 1, 1)": "John Scott Medal, Blue Plaque",
  "(6, 0, 2)": "Scientific career",
  "(7, 0, 1)": "Fields",
  "(7, 1, 1)": "inventor"
}