{
  "(0, 0, 2)": "Dean Kamen",
  "(1, 0, 1)": "Born",
  "(1, 1, 1)": "(1951-04-05) April 5, 1951 (age 67)",
  "(1, 2, 1)": "Long Island, New York, U.S.",
  "(2, 0, 1)": "Residence",
  "(2, 1, 1)": "Bedford, New Hampshire, U.S.",
  "(3, 0, 1)": "Nationality",
  "(3, 1, 1)": "American",
  "(4, 0, 1)": "Known for",
  "(4, 1, 1)": "Invention of the iBot Wheelchair, the Segway and founder of FIRST",
  "(4, 2, 1)": "North Dumpling Island",
  "(5, 0, 1)": "Awards",
  "(5, 1, 1)": "Hoover Medal (1995)",
  "(5, 2, 1)": "Heinz Award in Technology, the Economy and Employment  (1999)",
  "(5, 3, 1)": "National Medal of Technology and Innovation (2000)",
  "(5, 4, 1)": "Lemelson MIT Prize (2002)",
  "(5, 5, 1)": "ASME Medal (2007)",
  "(5, 6, 1)": "Lindbergh Award (2011)",
  "(5, 7, 1)": "Global Humanitarian Award (2013)"
}