{
  "(0, 0, 2)": "Kingdom of Cambodia",
  "(0, 1, 1)": "ព្រះរាជាណាចក្រកម្ពុជា (Khmer)",
  "(0, 2, 1)": "prĕ h ri ci naacak kampuci ",
  "(0, 3, 1)": "Royaume du Cambodge  (French)",
  "(1, 0, 1)": "Capital",
  "(1, 1, 1)": "and largest city",
  "(1, 2, 1)": "Phnom Penh",
  "(1, 3, 1)": "11°33′N 104°55′E﻿ / ﻿11.550°N 104.917°E﻿ / 11.550; 104.917Coordinates: 11°33′N 104°55′E﻿ / ﻿11.550°N 104.917°E﻿ / 11.550; 104.917",
  "(2, 0, 1)": "Official languages",
  "(2, 1, 1)": "Khmer",
  "(3, 0, 1)": "Spoken languages",
  "(3, 1, 1)": "Khmer",
  "(3, 2, 1)": "Cham",
  "(3, 3, 1)": "French",
  "(4, 0, 1)": "Official script",
  "(4, 1, 1)": "Khmer script",
  "(5, 0, 1)": "Ethnic groups  (2013)",
  "(5, 1, 1)": "97.6% Khmer",
  "(5, 2, 1)": "1.2% Chams",
  "(5, 3, 1)": "0.1% Vietnamese",
  "(5, 4, 1)": "0.1% Chinese",
  "(5, 5, 1)": "1% other",
  "(6, 0, 1)": "Religion  (2010)",
  "(6, 1, 1)": "96.9% Buddhism (official)",
  "(6, 2, 1)": "2.0% Islam",
  "(6, 3, 1)": "0.5% Folk religion",
  "(6, 4, 1)": "0.4% Christianity",
  "(6, 5, 1)": "0.2% unaffiliated",
  "(7, 0, 1)": "Demonym(s)",
  "(7, 1, 1)": "Cambodian",
  "(7, 2, 1)": "Khmer",
  "(8, 0, 1)": "Government",
  "(8, 1, 1)": "Unitary dominant-party parliamentary elective constitutional monarchy (de jure) under an one-party state authoritarian dictatorship (de facto)",
  "(9, 0, 1)": "• King ",
  "(9, 1, 1)": "Norodom Sihamoni",
  "(10, 0, 1)": "• Prime Minister ",
  "(10, 1, 1)": "Hun Sen",
  "(11, 0, 1)": "• President of the Senate ",
  "(11, 1, 1)": "Say Chhum",
  "(12, 0, 1)": "• President of the National Assembly ",
  "(12, 1, 1)": "Heng Samrin",
  "(13, 0, 1)": "Legislature",
  "(13, 1, 1)": "Parliament",
  "(14, 0, 1)": "• Upper house",
  "(14, 1, 1)": "Senate",
  "(15, 0, 1)": "• Lower house",
  "(15, 1, 1)": "National Assembly"
}